konfig_master/__init__.py
konfig_master/core.py
konfig_master-0.1.1.dist-info/METADATA
konfig_master-0.1.1.dist-info/WHEEL
konfig_master-0.1.1.dist-info/licenses/LICENSE
konfig_master-0.1.1.dist-info/RECORD
