Metadata-Version: 2.4
Name: konfig-master
Version: 0.1.1
Summary: A simple, unified interface for managing application configuration.
Project-URL: Homepage, https://github.com/swapnillader/konfig-master
Project-URL: Bug Tracker, https://github.com/swapnillader/konfig-master/issues
Author-email: Swapnil Prakash Lader <swapnillader@gmail.com>
License-File: LICENSE
Keywords: config,configuration,json,settings,toml,yaml
Classifier: License :: OSI Approved :: MIT License
Classifier: Operating System :: OS Independent
Classifier: Programming Language :: Python :: 3
Classifier: Topic :: Software Development :: Libraries :: Python Modules
Requires-Python: >=3.8
Requires-Dist: pyyaml>=6.0
Requires-Dist: toml>=0.10.2
